{
    "Elements":
    [
        {
            "ID": "Window1",
            "Type": "Window"
        },
        {
            "Parent": "Window1",
            "ID": "WelcomeText",
            "Type": "Text",

            "Text": "The Maze Is Lava",
            "xAlignment": "Center",
            "yAlignment": "Top",
            "y": -50
        },
        {
            "Parent": "Window1",
            "ID": "WelcomeInstructions",
            "Type": "Text",
            "Text": "Press enter to continue",

            "xAlignment": "Center",
            "yAlignment": "Top",
            "x": -50
        }
    ]
}